esewa/__init__.py
esewa/client.py
esewa/exceptions.py
esewa/utils.py
esewa-0.2.1.dist-info/licenses/LICENSE
esewa-0.2.1.dist-info/METADATA
esewa-0.2.1.dist-info/WHEEL
esewa-0.2.1.dist-info/top_level.txt
esewa-0.2.1.dist-info/RECORD
