Metadata-Version: 2.4
Name: esewa
Version: 0.2.1
Summary:  A Python client for eSewa integration
Author-email: Sahil Dahal <the.sahil.verse@gmail.com>
License-Expression: MIT
Project-URL: Homepage, https://github.com/sahilverse/esewa-python
Requires-Python: >=3.12
License-File: LICENSE
Requires-Dist: requests>=2.25.1
Dynamic: license-file
